[
    {
        "key": "dbln",
        "value": "%7B%2261555980650434%22%3A%22B3oH6k6H%22%7D",
        "domain": "facebook.com",
        "path": "/login/device-based/",
        "hostOnly": false,
        "creation": "2025-05-17T12:36:46.454Z",
        "lastAccessed": "2025-05-17T12:36:46.466Z"
    },
    {
        "key": "datr",
        "value": "0gEoaNEBhFDEctmEzKHi0nGl",
        "domain": "facebook.com",
        "path": "/",
        "hostOnly": false,
        "creation": "2025-05-17T12:36:46.466Z",
        "lastAccessed": "2025-05-17T12:36:46.466Z"
    },
    {
        "key": "sb",
        "value": "0gEoaOaBtYPk_WxA2lK0D_nt",
        "domain": "facebook.com",
        "path": "/",
        "hostOnly": false,
        "creation": "2025-05-17T12:36:46.466Z",
        "lastAccessed": "2025-05-17T12:36:46.466Z"
    },
    {
        "key": "dpr",
        "value": "1.7937500476837158",
        "domain": "facebook.com",
        "path": "/",
        "hostOnly": false,
        "creation": "2025-05-17T12:36:46.466Z",
        "lastAccessed": "2025-05-17T12:36:46.466Z"
    },
    {
        "key": "wd",
        "value": "979x1853",
        "domain": "facebook.com",
        "path": "/",
        "hostOnly": false,
        "creation": "2025-05-17T12:36:46.466Z",
        "lastAccessed": "2025-05-17T12:36:46.466Z"
    },
    {
        "key": "c_user",
        "value": "61555980650434",
        "domain": "facebook.com",
        "path": "/",
        "hostOnly": false,
        "creation": "2025-05-17T12:36:46.466Z",
        "lastAccessed": "2025-05-17T12:36:46.466Z"
    },
    {
        "key": "fr",
        "value": "1uS6LpyEN4vE1GcA2.AWc3M4ctt6_bINQsO8YvnGDhcYCDebRdEerJ4S2Bz6Eusf2UV-w.BoKIK2..AAA.0.0.BoKIK2.AWfAaejfZeAbEd6AWgB5YL6fYJQ",
        "domain": "facebook.com",
        "path": "/",
        "hostOnly": false,
        "creation": "2025-05-17T12:36:46.466Z",
        "lastAccessed": "2025-05-17T12:36:46.466Z"
    },
    {
        "key": "xs",
        "value": "14%3ANbGLYIrPeJo34Q%3A2%3A1747452557%3A-1%3A6296%3A%3AAcUC2nm-iSAQDMhoMkRLLaAk0lQoG9CBTNO5zvx81A",
        "domain": "facebook.com",
        "path": "/",
        "hostOnly": false,
        "creation": "2025-05-17T12:36:46.466Z",
        "lastAccessed": "2025-05-17T12:36:46.466Z"
    },
    {
        "key": "presence",
        "value": "C%7B%22t3%22%3A%5B%5D%2C%22utc3%22%3A1747485406188%2C%22v%22%3A1%7D",
        "domain": "facebook.com",
        "path": "/",
        "hostOnly": false,
        "creation": "2025-05-17T12:36:46.466Z",
        "lastAccessed": "2025-05-17T12:36:46.466Z"
    }
]
